sme_sdk/__init__.py
sme_sdk/api.py
sme_sdk/blob.py
sme_sdk/config.py
sme_sdk/exceptions.py
sme_sdk/types.py
sme_sdk/urls.py
sme_sdk/utils.py
cardo_sme_sdk-0.3.3.dist-info/LICENCE
cardo_sme_sdk-0.3.3.dist-info/METADATA
cardo_sme_sdk-0.3.3.dist-info/WHEEL
cardo_sme_sdk-0.3.3.dist-info/top_level.txt
cardo_sme_sdk-0.3.3.dist-info/RECORD
