Metadata-Version: 2.1
Name: cardo-sme-sdk
Version: 0.3.3
Summary: SME Service SDK in Python
Home-page: UNKNOWN
Author: Klement Omeri
Author-email: hello@cardoai.com
License: MIT
Project-URL: Documentation, https://docs.service.cardoai.com/sme_sdk/index.html
Project-URL: Source, https://github.com/CardoAI/sme_python
Platform: UNKNOWN
Classifier: Development Status :: 4 - Beta
Classifier: Intended Audience :: Developers
Classifier: Topic :: Software Development :: Build Tools
Classifier: License :: OSI Approved :: MIT License
Classifier: Programming Language :: Python :: 3
Classifier: Programming Language :: Python :: 3.6
Classifier: Programming Language :: Python :: 3.7
Classifier: Programming Language :: Python :: 3.8
Classifier: Programming Language :: Python :: 3.9
Classifier: Programming Language :: Python :: 3.10
Requires-Python: >=3.6
License-File: LICENCE
Requires-Dist: boto3 (>=1.20.27)
Requires-Dist: requests (>=2.27.1)
Provides-Extra: dev
Requires-Dist: pytest (>=7) ; extra == 'dev'
Requires-Dist: pytest-cov (>=3) ; extra == 'dev'
